pearsend.py
pearsend-0.0.3.dist-info/DESCRIPTION.rst
pearsend-0.0.3.dist-info/METADATA
pearsend-0.0.3.dist-info/RECORD
pearsend-0.0.3.dist-info/WHEEL
pearsend-0.0.3.dist-info/entry_points.txt
pearsend-0.0.3.dist-info/metadata.json
pearsend-0.0.3.dist-info/top_level.txt
